pretty_talib/__init__.py
pretty_talib/func_details.py
pretty_talib/pretty_talib.py
pretty_talib/returns.py
pretty_talib/enums/__init__.py
pretty_talib/enums/function_name.py
pretty_talib-0.0.10.dist-info/LICENSE
pretty_talib-0.0.10.dist-info/METADATA
pretty_talib-0.0.10.dist-info/WHEEL
pretty_talib-0.0.10.dist-info/top_level.txt
pretty_talib-0.0.10.dist-info/RECORD
