Metadata-Version: 2.1
Name: pretty-talib
Version: 0.0.10
Summary: prettified interface for TA-Lib
Home-page: https://github.com/kkristof200/pretty-TA-Lib
Author: Kristof
License: UNKNOWN
Platform: UNKNOWN
Classifier: Programming Language :: Python :: 3
Classifier: License :: OSI Approved :: MIT License
Classifier: Operating System :: OS Independent
Requires-Python: >=3.5
Requires-Dist: TA-Lib
Requires-Dist: jsoncodable
Requires-Dist: pandas
Requires-Dist: funcmeasure
Requires-Dist: numpy
Requires-Dist: talib
